pytest_pagerduty/__init__.py
pytest_pagerduty/plugin.py
pytest_pagerduty-1.0.0.dist-info/licenses/LICENSE.md
tests/integration/__init__.py
tests/integration/test_plugin.py
tests/unit/__init__.py
tests/unit/test_plugin.py
pytest_pagerduty-1.0.0.dist-info/METADATA
pytest_pagerduty-1.0.0.dist-info/WHEEL
pytest_pagerduty-1.0.0.dist-info/top_level.txt
pytest_pagerduty-1.0.0.dist-info/RECORD
