Metadata-Version: 2.4
Name: pytest-pagerduty
Version: 1.0.0
Summary: Pytest plugin for PagerDuty integration via automation testing.
Author-email: Oleg Matskiv <alpaca00tuha@gmail.com>
License: MIT
Keywords: pytest,pagerduty,pagerduty-api,alerting,monitoring,testing,QC
Requires-Python: >=3.8
License-File: LICENSE.md
Requires-Dist: pagerduty<2.0.0,>=1.0.0
Requires-Dist: pytest<9.0.0,>=7.4.0
Dynamic: license-file
